fast_sqlalchemy/__init__.py
fast_sqlalchemy/authentication/dependencies.py
fast_sqlalchemy/cli/__init__.py
fast_sqlalchemy/cli/commands.py
fast_sqlalchemy/cli/entry_point.py
fast_sqlalchemy/config/__init__.py
fast_sqlalchemy/config/exceptions.py
fast_sqlalchemy/config/utils.py
fast_sqlalchemy/config/yaml.py
fast_sqlalchemy/event_bus/__init__.py
fast_sqlalchemy/event_bus/bus.py
fast_sqlalchemy/event_bus/contexts.py
fast_sqlalchemy/event_bus/emit.py
fast_sqlalchemy/event_bus/middlewares.py
fast_sqlalchemy/logging/__init__.py
fast_sqlalchemy/logging/formatter.py
fast_sqlalchemy/logging/handlers.py
fast_sqlalchemy/logging/middlewares.py
fast_sqlalchemy/persistence/__init__.py
fast_sqlalchemy/persistence/context.py
fast_sqlalchemy/persistence/database.py
fast_sqlalchemy/persistence/middlewares.py
fast_sqlalchemy/py.typed
fast_sqlalchemy/testing/__init__.py
fast_sqlalchemy/testing/db_client.py
fast_sqlalchemy/testing/pytest.py
fast_sqlalchemy/translation/__init__.py
fast_sqlalchemy/translation/pydantic.py
fast_sqlalchemy-0.12.2.dist-info/entry_points.txt
fast_sqlalchemy-0.12.2.dist-info/WHEEL
fast_sqlalchemy-0.12.2.dist-info/METADATA
fast_sqlalchemy-0.12.2.dist-info/RECORD
