Metadata-Version: 2.1
Name: fast-sqlalchemy
Version: 0.12.2
Summary: Make application with Fastapi and Sqlalchemy with ease
Home-page: https://github.com/Chaisenbois/fast-alchemy
License: MIT
Author: Clement_Hue
Author-email: clementhue@hotmail.fr
Requires-Python: >=3.8,<4.0
Classifier: Environment :: Web Environment
Classifier: Framework :: AsyncIO
Classifier: Framework :: FastAPI
Classifier: Intended Audience :: Developers
Classifier: License :: OSI Approved :: MIT License
Classifier: Operating System :: OS Independent
Classifier: Programming Language :: Python :: 3
Classifier: Programming Language :: Python :: 3 :: Only
Classifier: Programming Language :: Python :: 3.10
Classifier: Programming Language :: Python :: 3.8
Classifier: Programming Language :: Python :: 3.9
Classifier: Programming Language :: Python :: Implementation :: CPython
Classifier: Topic :: Internet :: WWW/HTTP :: HTTP Servers
Classifier: Topic :: Software Development :: Libraries :: Python Modules
Requires-Dist: Jinja2 (>=3.1.2,<4.0.0)
Requires-Dist: PyJWT (>=2.4.0,<3.0.0)
Requires-Dist: PyYAML (>=6.0,<7.0)
Requires-Dist: SQLAlchemy (>=1.4.40,<2.0.0)
Requires-Dist: SQLAlchemy-Utils (>=0.38.3,<0.39.0)
Requires-Dist: alembic (>=1.8.1,<2.0.0)
Requires-Dist: factory-boy (>=3.2.1,<4.0.0)
Requires-Dist: fastapi (>=0.79.0,<0.80.0)
Requires-Dist: html2text (>=2020.1.16,<2021.0.0)
Requires-Dist: pyhumps (>=3.7.2,<4.0.0)
Requires-Dist: python-dotenv (>=0.20.0,<0.21.0)
Project-URL: Repository, https://github.com/Chaisenbois/fast-alchemy
